facebook_page_scraper/__init__.py
facebook_page_scraper/driver_initialization.py
facebook_page_scraper/driver_utilities.py
facebook_page_scraper/element_finder.py
facebook_page_scraper/scraper.py
facebook_page_scraper/scraping_utilities.py
facebook_page_scraper-5.0.6.dist-info/LICENSE
facebook_page_scraper-5.0.6.dist-info/METADATA
facebook_page_scraper-5.0.6.dist-info/WHEEL
facebook_page_scraper-5.0.6.dist-info/top_level.txt
facebook_page_scraper-5.0.6.dist-info/RECORD
