Metadata-Version: 2.1
Name: facebook_page_scraper
Version: 5.0.6
Summary: Python package to scrap facebook's pages front end with no limitations
Home-page: https://github.com/shaikhsajid1111/facebook_page_scraper
Author: Sajid Shaikh
Author-email: shaikhsajid3732@gmail.com
License: MIT
Keywords: web-scraping selenium facebook facebook-pages
Classifier: Development Status :: 4 - Beta
Classifier: Environment :: Console
Classifier: Intended Audience :: Developers
Classifier: Intended Audience :: Science/Research
Classifier: Natural Language :: English
Classifier: Programming Language :: Python :: 3
Classifier: Programming Language :: Python :: 3.6
Classifier: Programming Language :: Python :: 3.7
Classifier: Programming Language :: Python :: 3.8
Classifier: Programming Language :: Python :: 3.9
Classifier: Programming Language :: Python :: Implementation :: CPython
Classifier: License :: OSI Approved :: MIT License
Classifier: Operating System :: Microsoft :: Windows
Classifier: Operating System :: POSIX :: Linux
Classifier: Operating System :: MacOS
Classifier: Topic :: Software Development :: Libraries :: Python Modules
Classifier: Topic :: Internet :: WWW/HTTP
Requires-Python: >=3.7
License-File: LICENSE
Requires-Dist: selenium ==4.1.0
Requires-Dist: webdriver-manager ==3.2.2
Requires-Dist: selenium-wire ==5.1.0
Requires-Dist: python-dateutil ==2.8.2
